{"eventList":[{"year":"306年","titleList":["馬克森提烏斯成为羅馬皇帝。"]},{"year":"312年","titleList":["君士坦丁一世击败马克森提，统一羅馬帝國。"]},{"year":"1277年","titleList":["大都（今北京）日全食。"]},{"year":"1492年","titleList":["克里斯托弗·哥伦布在古巴靠岸。"]},{"year":"1538年","titleList":["首間新大陸大學成立。"]},{"year":"1707年","titleList":["日本發生強烈有感地震，至少5000人死亡。"]},{"year":"1868年","titleList":["爱迪生申请生平第一项专利，电子投票记录仪。"]},{"year":"1886年","titleList":["美国总统格罗弗·克利夫兰在紐約港主持法国赠送的自由女神像的揭幕仪式。"]},{"year":"1893年","titleList":["俄羅斯浪漫樂派作曲家柴可夫斯基在聖彼得堡指揮首演第六交響曲《悲愴》，並於九天後死於家中。"]},{"year":"1911年","titleList":["九广铁路英段与华段接轨，铁路全线通车。"]},{"year":"1914年","titleList":["行刺斐迪南凶手普林西普入狱。"]},{"year":"1918年","titleList":["从奥匈帝国独立的捷克与斯洛伐克合併，捷克斯洛伐克共和国成立。"]},{"year":"1922年","titleList":["意大利国家法西斯党领导人贝尼托·墨索里尼率领支持者发动“向罗马进军”的行动，以夺取意大利政权。"]},{"year":"1928年","titleList":["珍贵宝石印度之星被窃[來源請求]。"]},{"year":"1929年","titleList":["世界經濟遭遇大蕭條。"]},{"year":"1940年","titleList":["意大利要求占领希腊领土的最后通牒被拒绝，意大利军队入侵希腊，希腊意大利战争爆发。"]},{"year":"1942年","titleList":["奧許維茲集中營有240名波蘭年輕人遭到集體槍決，大部分來自盧布林，後稱「盧布林鎮壓」。"]},{"year":"1942年","titleList":["克拉科夫-普拉佐集中營啟用。"]},{"year":"1945年","titleList":["赵树理发表《小二黑结婚》[來源請求]"]},{"year":"1950年","titleList":["中华人民共和国与芬兰共和国建交。"]},{"year":"1962年","titleList":["古巴导弹危机"]},{"year":"1962年","titleList":["新聞〈中國桌球隊女選手韓玉珍遭到日本歹徒襲擊〉轟動世界，後被證實是個選手製造的「假新聞」。"]},{"year":"1970年","titleList":["意大利恐怖组织红色旅成立。"]},{"year":"1977年","titleList":["香港警廉衝突。"]},{"year":"1979年","titleList":["日本御岳山火山突然爆发。"]},{"year":"1979年","titleList":["萨尔瓦多内战[來源請求]。"]},{"year":"1986年","titleList":["心肺同时移植首次在西班牙完成[來源請求]。"]},{"year":"1988年","titleList":["法国发射第一颗电视直播卫星[1]。"]},{"year":"1990年","titleList":["香港維多利亞公園一萬人集會保衛釣魚台。"]},{"year":"1992年","titleList":["叶爾钦解散俄民族救国阵线组委会[來源請求]"]},{"year":"1992年","titleList":["埃及赛德港因油轮被撞进入紧急状态。"]},{"year":"1993年","titleList":["馬家軍體育界醜聞，事件調查出來被禁止出版，直到2016年曝光。"]},{"year":"1995年","titleList":["科克伦走钢丝跨越夔门天堑。"]},{"year":"1995年","titleList":["阿塞拜疆巴库地铁失火死伤惨重。"]},{"year":"1996年","titleList":["拉贝日记发表。"]},{"year":"1997年","titleList":["黄河小浪底工程胜利截流。"]},{"year":"1998年","titleList":["一架中国国际航空公司客机被劫持到台灣。"]},{"year":"1998年","titleList":["義大利電影海上鋼琴師上映。"]},{"year":"2002年","titleList":["意大利西西里岛上的活火山埃特纳火山出现大规模的喷发。"]},{"year":"2002年","titleList":["新修订的《中华人民共和国文物保护法》正式实施。"]},{"year":"2007年","titleList":["克里斯蒂娜·費爾南德斯當選成為首位阿根廷經民主選舉產生的女總統。"]},{"year":"2007年","titleList":["統一獅在中華職棒18年總冠軍賽擊敗La new熊，獲得年度總冠軍。"]},{"year":"2013年","titleList":["北京天安門廣場發生恐怖襲擊，3名恐怖分子駕駛一輛吉普車，衝向行人路，撞倒路上的途人，然後撞向金水橋，實施自爆。"]},{"year":"2016年","titleList":["韓國外交官楊昌洙經青瓦台委任為駐台北韓國代表部新任代表[2]。"]},{"year":"2018年","titleList":["重慶萬州巴士墜江事故"]}],"birthList":[{"year":"1818年","titleList":["伊凡·屠格涅夫，俄国现实主义小说家、诗人、剧作家（逝於1883年）"]},{"year":"1860年","titleList":["嘉納治五郎，日本柔道的創始人（逝於1938年）"]},{"year":"1885年","titleList":["赫列布尼科夫（英语"]},{"year":"1894年","titleList":["叶圣陶，中国现代作家、教育家及出版人。（1988年逝世）"]},{"year":"1914年","titleList":["喬納斯·索爾克，又譯為約納斯·沙克，小兒麻痺疫苗發明者。（1995年逝世）"]},{"year":"1941年","titleList":["濱田晃（日语"]},{"year":"1947年","titleList":["馬海倫，香港演員"]},{"year":"1953年","titleList":["朴英奎，韓國演員"]},{"year":"1955年","titleList":["比爾蓋茲，是一名美國著名企業家、軟體工程師、慈善家以及微軟公司的董事長"]},{"year":"1959年","titleList":["增田俊郎，日本作曲家"]},{"year":"1960年","titleList":["福田己津央，日本動畫導演"]},{"year":"1963年","titleList":["郭耀明，香港演員"]},{"year":"1964年","titleList":["尹天照，香港演員"]},{"year":"1967年","titleList":["茱莉亞·羅勃茲，美國好萊塢演員"]},{"year":"1966年","titleList":["陳法蓉，香港演員"]},{"year":"1968年","titleList":["張子健，中國男演員"]},{"year":"1968年","titleList":["史蒂芬·杭特，紐西蘭男演員[3]"]},{"year":"1971年","titleList":["陳建寧，華納唱片音樂總監、台灣著名音樂人、F.I.R.團長"]},{"year":"1973年","titleList":["瑪麗安·納瓦茲·謝里夫，巴基斯坦女政治人物"]},{"year":"1974年","titleList":["祖昆·馮力士，美國電影演員、音樂人"]},{"year":"1976年","titleList":["金瑞馨，韓國女演员"]},{"year":"1976年","titleList":["夏雨，中國男演員"]},{"year":"1977年","titleList":["陳金鋒，是第一位在美國職棒大聯盟比賽中登場的台灣選手"]},{"year":"1978年","titleList":["關朵琳·克莉絲蒂，英国女演員"]},{"year":"1980年","titleList":["阿倫·史密夫，英国足球运动员"]},{"year":"1981年","titleList":["巴路士，捷克足球運動員"]},{"year":"1982年","titleList":["倉木麻衣，日本女歌手"]},{"year":"1982年","titleList":["福井裕佳梨，日本女性聲優"]},{"year":"1983年","titleList":["NEEKO，日本模特兒及聲優"]},{"year":"1984年","titleList":["袁嘉敏，香港女演員"]},{"year":"1985年","titleList":["崔宇革，韓國男演員"]},{"year":"1986年","titleList":["翁滋蔓，台灣女演員和歌手"]},{"year":"1986年","titleList":["豐崎愛生，日本女性聲優"]},{"year":"1986年","titleList":["艾迪蒂·拉·哈亞里，印度女演員"]},{"year":"1987年","titleList":["杜海濤，中國節目主持人"]},{"year":"1988年","titleList":["何浩文，香港男歌手"]},{"year":"1988年","titleList":["張天愛，中國女演員"]},{"year":"1989年","titleList":["卡蜜爾·莫法特，法國女子游泳運動員（2015年逝世）"]},{"year":"1997年","titleList":["昀昀，韓國男子偶像團體NCT成員"]}],"deathList":[{"year":"1704年","titleList":["约翰·洛克，英国哲学家、经验主义的开创人（1632年出生）"]},{"year":"1929年","titleList":["伯恩哈德·冯·比洛，德國首相（1849年出生）"]},{"year":"1937年","titleList":["官惠民，中华民国国民革命军将领（1901年出生）"]},{"year":"1937年","titleList":["刘眉生，中华民国国民革命军将领（1905年出生）"]},{"year":"1973年","titleList":["塔哈·侯賽因，埃及作家（1889年出生）"]},{"year":"1980年","titleList":["何非凡，香港粵劇演員（1919年出生）"]},{"year":"1998年","titleList":["泰德·休斯，英國桂冠詩人（1930年出生）"]},{"year":"2004年","titleList":["羅莎琳德·希克斯，作家阿加莎·克里斯蒂的女兒及文學遺產管理者（1919年出生）[4]"]},{"year":"2006年","titleList":["霍英東，香港商人，中國人民政治協商會議第八、九、十屆全國委員會副主席（1923年出生）"]},{"year":"2008年","titleList":["孔德成，孔子七十七代嫡長孫，衍聖公，大成至聖先師奉祀官（1920年出生）"]},{"year":"2010年","titleList":["梁从诫，知名环保人士、环保组织自然之友会长。著名建筑学家梁思成与林徽因之子，著名革命家及戊戌變法領袖，学者梁啟超之孫。（1932年出生）"]},{"year":"2013年","titleList":["塔德烏什·馬佐維耶茨基，二戰後中歐和東歐第一個非共產主義總理[5]（1927年出生）。"]},{"year":"2013年","titleList":["川上哲治，日本棒球運動員。（1920年出生）"]}],"holidayList":["联合国卫生组织的男性健康日","世界動畫日（World Animation Day）──加拿大政府於2007年所訂定。（International Animation Day（英语：International Animation Day）），国际动画协会International Animated Film Association（英语：ASIFA），2002年起。"]}