{"eventList":[{"year":"1606年","titleList":["英国文学家莎士比亚创作的戏剧《李尔王》进行了首次有记载的演出。"]},{"year":"1792年","titleList":["路易十六在巴黎接受審判。"]},{"year":"1871年","titleList":["英国戏剧合作伙伴吉尔伯特与沙利文合作的首部歌剧《泰斯庇斯》在伦敦首演。"]},{"year":"1898年","titleList":["法国化学家皮埃尔·居里和玛丽亚·居里夫妇公布发现了一种新的元素，后来命名为镭。"]},{"year":"1916年","titleList":["霞飛為法國元帥。"]},{"year":"1946年","titleList":["佛朗明哥飯店在拉斯維加斯開幕。"]},{"year":"1970年","titleList":["中国第一艘核潜艇091型核潜艇“长征1号”下水。"]},{"year":"1974年","titleList":["澳洲達爾文港風災後重建。"]},{"year":"1975年","titleList":["第一个得以超过2马赫飞行的商业航空器Tu-144开始投入服务。"]},{"year":"1986年","titleList":["香港仔避風塘發生四級大火。"]},{"year":"1989年","titleList":["南京反非洲人抗議事件開始。"]},{"year":"1990年","titleList":["福清县撤县建市。"]},{"year":"1991年","titleList":["苏联最高苏维埃召开最后一次会议并宣布解散。"]},{"year":"1993年","titleList":["中國大陸各地舉行各種活動紀念已故中共中央主席毛泽东誕辰一百週年。"]},{"year":"2001年","titleList":["有史以來全球第二最接近赤道形成的熱帶氣旋「畫眉」於新加坡近海形成。"]},{"year":"2003年","titleList":["伊朗东南部城市巴姆郡发生强烈地震，約26,000人死亡，30,000人。"]},{"year":"2004年","titleList":["印尼蘇門達臘對開印度洋發生強烈地震，并引发强烈海啸，约30万人遇难或失蹤，詳見2004年印度洋大地震。"]},{"year":"2006年","titleList":["台灣恆春發生黎克特制7.0級地震，2死42傷。"]},{"year":"2009年","titleList":["武广客运专线开通运营。"]},{"year":"2011年","titleList":["廣深港高速鐵路廣深段开通运营。"]},{"year":"2012年","titleList":["京石客运专线及石武客运专线石家莊至鄭州段开通运营，代表京廣高速鐵路全線貫通。"]},{"year":"2013年","titleList":["中國大陸各地舉行各種活動紀念已故中共中央主席毛泽东誕辰一百二十週年。[1]"]},{"year":"2015年","titleList":["成渝客运专线开通运营。"]},{"year":"2016年","titleList":["长株潭城际铁路、兰渝线岷县-广元段、合肥地铁1号线以及昆明地铁1号线支线正式通车。"]},{"year":"2017年","titleList":["合肥地铁2号线正式通车。[2]"]}],"birthList":[{"year":"1194年","titleList":["腓特烈二世，神圣罗马帝国皇帝（逝於1250年）"]},{"year":"1536年","titleList":["李珥，李氏朝鮮儒學者，2006年新版5000韓元正面肖像人物（逝於1584年）"]},{"year":"1791年","titleList":["查尔斯·巴贝奇，英國數學家、哲學家、機械工程學家（逝於1871年）"]},{"year":"1837年","titleList":["乔治·杜威，美國海軍特級上將（逝於1917年）"]},{"year":"1864年","titleList":["丘逢甲，台灣詩人、教育家。（逝於1912年）"]},{"year":"1867年","titleList":["潘佩珠，越南獨立運動革命家（逝於1940年）"]},{"year":"1872年","titleList":["诺曼·安吉尔，英國演講家、作家、英國工黨國會議員，1933年諾貝爾和平獎得主（逝於1967年）"]},{"year":"1880年","titleList":["埃尔顿·梅奥，澳洲心理學家、社会学家（逝於1949年）"]},{"year":"1887年","titleList":["白思華，英國陸軍將領（逝於1966年）"]},{"year":"1891年","titleList":["亨利·米勒，美國作家、業餘畫家，文壇怪傑（逝於1980年）"]},{"year":"1893年","titleList":["毛泽东，中国共产党第一任中央委员会主席，中国共产党、中华人民共和国和中国人民解放军的主要缔造者（逝於1976年）"]},{"year":"1907年","titleList":["老艾伯特·戈尔，美國田納西州聯邦參議員，美國第45任副總統艾伯特·戈尔之父（逝於1998年）"]},{"year":"1918年","titleList":["乔治·拉利斯，希臘前總理（逝於2006年）"]},{"year":"1920年","titleList":["麥理浩勳爵夫人，第25任香港總督麥理浩勳爵的妻子（逝於2020年）"]},{"year":"1929年","titleList":["龔育之，中國共產黨著名理論家（逝于2007年）"]},{"year":"1934年","titleList":["林黛，香港國語电影女演員（逝於1964年）"]},{"year":"1937年","titleList":["約翰·何頓·康威，英國數學家"]},{"year":"1937年","titleList":["纳辛贝·埃亚德马，多哥第五任總統（逝於2005年）"]},{"year":"1940年","titleList":["爱德华·普雷斯科特，美國经济学家，2004年诺贝尔经济学奖得主"]},{"year":"1947年","titleList":["大河原邦男，日本动画機械設定師"]},{"year":"1947年","titleList":["卡尔顿·费斯克，前美國職棒大聯盟捕手"]},{"year":"1949年","titleList":["若泽·拉莫斯·奥尔塔，东帝汶第2任總統"]},{"year":"1950年","titleList":["拉贾·佩尔韦兹·阿什拉夫，巴基斯坦總理"]},{"year":"1952年","titleList":["亞歷山大·安克瓦布，阿布哈茲第10任總理"]},{"year":"1953年","titleList":["蔡國權，香港男歌手"]},{"year":"1953年","titleList":["莱昂内尔·费尔南德斯，多明尼加共和國總統"]},{"year":"1953年","titleList":["托马斯·亨德里克·伊尔韦斯，愛沙尼亞總統"]},{"year":"1955年","titleList":["埃文·贝赫，美國參議院議員"]},{"year":"1959年","titleList":["森本晃司，日本動畫導演"]},{"year":"1959年","titleList":["王立军，中國原重慶市副市長、公安局局長，王立军事件主角"]},{"year":"1961年","titleList":["安德鲁·劳克，澳大利亞登山家"]},{"year":"1963年","titleList":["拉尔斯·乌尔里希，丹麥樂師，金屬樂隊鼓手和創始人"]},{"year":"1963年","titleList":["比尔·温宁顿，加拿大前職業籃球運動員"]},{"year":"1964年","titleList":["伊麗莎白·柯斯托娃，美國小說家"]},{"year":"1970年","titleList":["梁文道，香港文化人、傳媒人"]},{"year":"1971年","titleList":["傑瑞德·雷托，美國男演員、歌手"]},{"year":"1974年","titleList":["何超儀，香港女演員、歌手"]},{"year":"1975年","titleList":["马塞洛·里奥斯，智利職業網球運動員"]},{"year":"1976年","titleList":["李·德美，捷克國家跳水隊成員、色情女演員、成人模特兒（逝於2004年）"]},{"year":"1977年","titleList":["傅蔚冈，中国资深民间智库上海金融与法律研究院执行院长"]},{"year":"1978年","titleList":["中川里江，日本女性聲優"]},{"year":"1979年","titleList":["克里斯·道特雷，美國搖滾樂詞曲創作男歌手及吉他手"]},{"year":"1979年","titleList":["霍建華，台灣男演員"]},{"year":"1981年","titleList":["張穎康，香港男演員"]},{"year":"1982年","titleList":["小栗旬，日本男演員"]},{"year":"1982年","titleList":["刘芸，中國女演員"]},{"year":"1983年","titleList":["李野，中國短道速滑男子運動員"]},{"year":"1985年","titleList":["贝丝·贝尔斯，美國女演員"]},{"year":"1985年","titleList":["城田優，日本演員、歌手"]},{"year":"1986年","titleList":["雨果·洛里斯，法國足球運動員"]},{"year":"1986年","titleList":["基特·哈靈頓，英国男演員"]},{"year":"1988年","titleList":["能登有沙，日本女性聲優"]},{"year":"1989年","titleList":["秋山奈奈，日本女藝人"]},{"year":"1989年","titleList":["约翰·布莱克，牙買加短跑運動員"]},{"year":"1989年","titleList":["德井青空，日本女性聲優"]},{"year":"1990年","titleList":["阿隆·拉姆塞，威尔士足球員"]},{"year":"1991年","titleList":["佐香智久，日本唱作歌手"]},{"year":"1992年","titleList":["夏志明，香港足球員"]},{"year":"1992年","titleList":["松島莊汰（日语"]},{"year":"1993年","titleList":["胡一天，中國男演員"]},{"year":"1996年","titleList":["刘艺，中华人民共和国警察"]},{"year":"1999年","titleList":["吳磊，中國童星"]},{"year":"2000年","titleList":["山繆·謝維揚，美國西洋棋棋士，9歲又11個月15天時成為美國西洋棋協會史上最年輕的國家大師"]},{"year":"2001年","titleList":["Kyla，韓國女子團體Pristin成員"]}],"deathList":[{"year":"1944年","titleList":["朱生豪，翻译家（1912年出生）"]},{"year":"1968年","titleList":["荀慧生，中国著名京剧演员（1900年出生）"]},{"year":"1972年","titleList":["哈利·S·杜鲁门，美国总统（1884年出生）"]},{"year":"1987年","titleList":["梅爾福德·史蒂文森爵士，英國高等法院法官（1902年出生）"]},{"year":"1999年","titleList":["柯提斯·梅菲爾德，美國黑人靈魂樂歌手（1942年出生）"]},{"year":"2001年","titleList":["奈杰尔·霍桑，知名BBC政治喜剧是的大臣演员（1929年出生）"]},{"year":"2006年","titleList":["杰拉尔德·福特，美国总统（1913年出生）"]},{"year":"2009年","titleList":["栾义军，前八一足球俱乐部足球運動員（1967年出生）"]},{"year":"2011年","titleList":["高华，中国历史学家（1954年出生）"]},{"year":"2012年","titleList":["格里·安德森（英语"]}],"holidayList":["斯洛文尼亚独立节","節禮日。香港人普遍視此日為「拆礼物日」。","毛泽东诞辰日"]}