{"eventList":[{"year":"1639年","titleList":["为纪念约翰·哈佛，哈佛學院正式得名。"]},{"year":"1781年","titleList":["英国天文学家威廉·赫歇爾用自制的望远镜发现一颗新的行星——天王星。"]},{"year":"1881年","titleList":["俄国沙皇亚历山大二世遇刺身亡。"]},{"year":"1884年","titleList":["马赫迪起义"]},{"year":"1900年","titleList":["第二次波耳戰爭"]},{"year":"1901年","titleList":["钢铁大王安德魯·卡內基宣布退休。"]},{"year":"1905年","titleList":["日俄激战，俄军被迫放弃沈阳。"]},{"year":"1919年","titleList":["中国龙井地区发生3·13反日运动。"]},{"year":"1920年","titleList":["柏林发生保皇党未遂政变，史称卡普政變。"]},{"year":"1921年","titleList":["蒙古国在罗曼·冯·恩琴的领导下，宣布脱离中华民国，外蒙古独立。"]},{"year":"1938年","titleList":["奥地利併入德國。"]},{"year":"1943年","titleList":["纳粹德国党卫军进入克拉科夫犹太人区，将犹太人送往集中营强制劳动或杀害。"]},{"year":"1947年","titleList":["延安保卫战开始。"]},{"year":"1954年","titleList":["越南獨立同盟會的军队在武元甲的领导下向奠邊府的法国军队发动进攻，奠邊府戰役爆发。"]},{"year":"1972年","titleList":["中国和英国在北京签署联合公报，决定从即日起将双方派驻对方的外交代表由代办升格为大使。英国决定自本日起撤销其在台湾的官方代表机构。"]},{"year":"1979年","titleList":["欧洲共同体内部开始使用欧洲货币单位作为计价结算的一种货币单位。"]},{"year":"1979年","titleList":["毛里斯·毕肖普（英语"]},{"year":"1982年","titleList":["中国将计划生育定为一项基本国策。"]},{"year":"1984年","titleList":["台湾宣布实施“自由经济政策”。"]},{"year":"1988年","titleList":["连接日本本州岛与北海道岛的青函隧道正式通车，成为世界最长的海底隧道。"]},{"year":"1991年","titleList":["香港政府公佈社會福利白皮書。"]},{"year":"1997年","titleList":["當天晚上，V字型不明飛行物飛過鳳凰城，此不明飛行物稱為鳳凰城光點。[1][2]"]},{"year":"2000年","titleList":["美國國防部長威廉·科恩訪問越南，成為越戰結束25年來首位訪問越南的美國國防部長。"]},{"year":"2011年","titleList":["日本福島第一核電廠1號機組受三陸沖大地震影響發生冷卻系統故障，導致反應爐心溫度無法控制，在日本時間下午3時36分4左右，冒出白煙後傳出爆炸聲響，有4人受傷，並造成輻射外洩。"]},{"year":"2012年","titleList":["自初版面世以來歷時244年的大英百科全書將不再出版印刷版。"]},{"year":"2013年","titleList":["阿根廷籍樞機主教豪爾赫·馬里奧·贝戈格里奥被選為梵蒂岡第266任教宗方济各。"]}],"birthList":[{"year":"1084年","titleList":["李清照，南宋女詞人（逝世于1155年）"]},{"year":"1615年","titleList":["教宗英諾森十二世（逝世于1700年）"]},{"year":"1733年","titleList":["约瑟夫·普利斯特里，英国化学家（逝世于1804年）"]},{"year":"1741年","titleList":["约瑟夫二世，神圣罗马帝国皇帝（逝世于1790年）"]},{"year":"1753年","titleList":["路易絲·瑪麗·阿德萊德·德·波旁，法国奥尔良公爵夫人（逝世于1821年）"]},{"year":"1855年","titleList":["帕西瓦尔·罗威尔，美國天文学家（逝世于1916年）"]},{"year":"1902年","titleList":["李梅樹，台灣藝術家（逝世于1983年）"]},{"year":"1939年","titleList":["李國寶，香港銀行家、政治人物"]},{"year":"1945年","titleList":["吉永小百合，日本女演員"]},{"year":"1947年","titleList":["蕭芳芳，香港電影女演員"]},{"year":"1955年","titleList":["何厚鏵，澳門特別行政區第一、二任行政長官"]},{"year":"1960年","titleList":["唐凱琳，英國外交官。"]},{"year":"1968年","titleList":["奧井雅美，日本女歌手"]},{"year":"1973年","titleList":["黃金寶，香港首席單車手"]},{"year":"1974年","titleList":["李慧琼，香港政界人物"]},{"year":"1977年","titleList":["謝安琪，香港女歌手"]},{"year":"1979年","titleList":["","陳怡蓉，臺灣女演員","尤漢·山塔納，美國棒球选手"]},{"year":"1982年","titleList":["","羽多野涉，日本動畫聲優","朱慧雯，美國女冰球運動員","李水京，韓國女演員","申愛，韓國女演員","櫻井良太，日本籃球運動員"]},{"year":"1984年","titleList":["","南里侑香，日本動畫聲優、歌手","喜屋武千秋，日本寫真偶像、女歌手","李浚赫，韓國男演員"]},{"year":"1986年","titleList":["大東駿介，日本男演員、模特兒"]},{"year":"1987年","titleList":["張培萌，2007年中國全國田徑錦標賽男子短跑冠軍、2007年夏季世界大學運動會短跑亞軍"]},{"year":"1991年","titleList":["","張藝洋，中國男演員、歌手","何杰，臺灣男歌手"]},{"year":"1991年","titleList":["權娜拉，韓國女子偶像團體Hello Venus成員"]},{"year":"1992年","titleList":["","喬治·麥凱，英国男演员","金明洙，韓國男子團體INFINITE成員、演員"]},{"year":"1994年","titleList":["中島健人，日本演員"]},{"year":"2001年","titleList":["崔范奎，韓國男子偶像團體TOMORROW X TOGETHER成員"]},{"year":"生年不详","titleList":["蔡民止（朝鲜语"]}],"deathList":[{"year":"1881年","titleList":["亞歷山大二世，俄羅斯帝國皇帝（1818年出生）"]},{"year":"1901年","titleList":["本杰明·哈里森，美國第二十三任總統（1833年出生）"]},{"year":"1906年","titleList":["苏珊·安东尼，美国女权主义活动家（1820年出生）"]},{"year":"1981年","titleList":["譚蘭卿，香港演员（1908年出生）"]},{"year":"1983年","titleList":["陶三姑，香港演员（1895年出生）"]},{"year":"2010年","titleList":["何平平，當今世界上身高最矮的男子（1988年出生）"]},{"year":"2014年","titleList":["王金河，台灣醫生，有「台灣烏腳病之父」美譽（1916年出生）"]}],"holidayList":[" 梵蒂冈：国庆日"]}