{"eventList":[{"year":"306年","titleList":["羅馬帝國皇帝君士坦提烏斯一世逝世，其子君士坦丁一世被他的军队拥立为新皇帝。"]},{"year":"1137年","titleList":["亞奎丹的艾莉諾與後來成為法國國王的路易王子在波爾多主教座堂成婚。"]},{"year":"1139年","titleList":["阿方索一世取得了对摩尔人的大胜，同时宣布称王，成为第一位葡萄牙国王。"]},{"year":"1261年","titleList":["由阿列克谢·斯特拉特哥普洛斯（英语"]},{"year":"1536年","titleList":["西班牙征服者贝拉尔卡萨尔率领探险队在哥伦比亚西部寻找黄金国时建立卡利城。"]},{"year":"1547年","titleList":["法蘭西國王亨利二世被加冕為王。"]},{"year":"1554年","titleList":["瑪麗一世與腓力二世在溫徹斯特座堂成婚。"]},{"year":"1593年","titleList":["法蘭西國王亨利四世從新教改信奉羅馬天主教。"]},{"year":"1603年","titleList":["蘇格蘭國王詹姆士六世加冕為英格蘭國王詹姆士一世，使得英格蘭王國與蘇格蘭王國合併為共主邦聯。後於1707年達成政治統一。"]},{"year":"1668年","titleList":["山东郯城一带发生8.5级大地震，压毙5万余人。"]},{"year":"1792年","titleList":["普鲁士元帅卡尔·威廉·斐迪南在科布伦茨发表宣言，声称如果法国国王路易十六及其王室成员受到伤害，将惩罚巴黎人民。"]},{"year":"1830年","titleList":["法国的查理十世宣布敕令，控制报界，解散立法机构并改变选举制度。"]},{"year":"1886年","titleList":["重庆教案发生。"]},{"year":"1894年","titleList":["甲午战争爆发。"]},{"year":"1898年","titleList":["张之洞所著《劝学篇》颁发各省。"]},{"year":"1909年","titleList":["法国飞行员布莱里奥驾驶飞机从法国加莱附近飞抵英国多佛尔，成为首个驾驶飞机飞越英吉利海峡的人。"]},{"year":"1914年","titleList":["袁世凯政府与英国宝林分公司签订一千万镑《沙兴铁路借款合同》。"]},{"year":"1917年","titleList":["日本光學工業株式會社（即現今的 尼康）成立"]},{"year":"1919年","titleList":["列宁领导下的苏维埃俄国政府发表致中国国民及南北政府宣言，废除帝俄对中国的一切不平等条约。"]},{"year":"1934年","titleList":["臺北帝國大學物理學講座教授荒勝文策成功在臺灣做出亞洲第一次，世界第二次人工撞擊原子核實驗，僅次於英國劍橋大學卡文迪许實驗室[1]。"]},{"year":"1951年","titleList":["中華民國國防部頒發首次徵兵令，為在台灣的第一次正式徵兵令[來源請求]。"]},{"year":"1954年","titleList":["中華民國國父遺教研究會成立[來源請求]。"]},{"year":"1958年","titleList":["台灣省政府會報通過「滅蠅運動」實施計劃，定於同年8月1日起實行。"]},{"year":"1957年","titleList":["法国国民议会投票准许突尼斯独立。"]},{"year":"1961年","titleList":["世界宗教徒和平会议在日本京都开幕[2]。"]},{"year":"1964年","titleList":["日本東海道新幹線開始試運轉。"]},{"year":"1966年","titleList":["台灣木柵興建中的考試大樓突然全部倒塌，造成3人死亡及多人受傷。"]},{"year":"1967年","titleList":["中華民國立法院通過關稅法[3]。"]},{"year":"1968年","titleList":["歐洲八國九大銀行同意對中華民國無限制提供商業貸款。[來源請求]"]},{"year":"1972年","titleList":["中華民國行政院廢止公務員三考三卡制[來源請求]。"]},{"year":"1978年","titleList":["中國與越南關係趨於惡化，越南當局開始排華，許多越南華僑滯留中越邊界，等待回國[來源請求]。"]},{"year":"1978年","titleList":["全球首位試管嬰兒露薏丝·布朗在英國誕生。"]},{"year":"1982年","titleList":["中国民航一架伊尔-18在从西安飞往上海的途中遭5人劫持，劫机者被机组人员和部分乘客制服，成为中国公开报道的首起劫机案。[4][5][6]"]},{"year":"1983年","titleList":["斯里蘭卡各地爆發種族暴動（英语"]},{"year":"1984年","titleList":["中華人民共和國第一家股份制企业北京天桥百货股份有限公司成立。[7]"]},{"year":"1984年","titleList":["中華人民共和國和英国关于香港问题第二阶段第十九轮会谈在北京举行。"]},{"year":"1992年","titleList":["第二十五屆奧林匹克運動會在西班牙巴塞隆拿開幕。"]},{"year":"1993年","titleList":["以色列軍隊開始炮轟（英语"]},{"year":"1995年","titleList":["“亚太二号”的爆炸原因公布。[8]"]},{"year":"1996年","titleList":["布隆迪发生军事政变（英语"]},{"year":"1997年","titleList":["中国跟库克群岛正式建交。"]},{"year":"1998年","titleList":["日本和歌山縣發生咖哩遭下毒事件，造成67人中毒，其中4人死亡。"]},{"year":"1998年","titleList":["美國海軍杜魯門號航空母艦正式服役。"]},{"year":"1998年","titleList":["《文汇报》和《新民晚报》组成文汇新民联合报业集团。"]},{"year":"2000年","titleList":["法國航空4590號班機在巴黎戴高樂機場起飞时坠毁，导致113人死亡。這是协和飞机首次亦是唯一一次空難。"]},{"year":"2004年","titleList":["蘭斯·阿姆斯特朗在環法自行車賽連續6年贏得冠軍。"]},{"year":"2006年","titleList":["2006年以黎衝突期間，以色列一枚炸彈擊中聯合國駐黎巴嫩的觀察員據點，四名國籍為中華人民共和國、奧地利、加拿大和芬蘭的聯合國觀察員殉難，時任聯合國秘書長科菲·安南和中國政府提出強烈抗議。"]},{"year":"2007年","titleList":["普拉蒂巴·帕蒂尔宣誓就任印度总统，成为印度第一位女总统。"]},{"year":"2010年","titleList":["因對時任廣州市政協提案委副主任纪可光提案的不滿，中國廣州發生捍衛粵語行動，8月1日在香港和廣州等地又同時發起第二次遊行。"]},{"year":"2016年","titleList":["臺灣立法院三讀通過「政黨及其附隨組織不當取得財產處理條例」以開始處理過往威權時期政黨不當取得財產的問題。"]},{"year":"2018年","titleList":["新西兰议会以63:57通过家暴受害者休假法案，允许其带薪休假。"]}],"birthList":[{"year":"1109年","titleList":["阿方索一世，葡萄牙的第一个国王（1185年逝世）"]},{"year":"1562年","titleList":["加藤清正，安土桃山时代、江户时代武将和大名（1611年逝世）"]},{"year":"1658年","titleList":["阿奇博尔德·坎贝尔，苏格兰贵族。第九代阿盖尔伯爵的长子（1703年逝世）"]},{"year":"1750年","titleList":["亨利·诺克斯，美国书商、军官、政治家，曾任美国战争部长（1806年逝世）"]},{"year":"1844年","titleList":["湯姆·艾金斯，美國畫家、攝影家（1916年逝世）"]},{"year":"1876年","titleList":["伊莉莎白，比利时王后（1965年逝世）"]},{"year":"1894年","titleList":["加夫里若·普林西普，塞尔维亚族民族主义者、刺客（1918年逝世）"]},{"year":"1896年","titleList":["约瑟芬·铁伊，英国著名推理小说家（1952年逝世）"]},{"year":"1905年","titleList":["艾里阿斯·卡内基，英国德语作家，于1981年荣获诺贝尔文学奖（1994年逝世）"]},{"year":"1916年","titleList":["郁風，中國散文家、畫家（2007年逝世）"]},{"year":"1920年","titleList":["羅莎琳·富蘭克林，英国生物化学和生物物理学家。在遗传基因方面有着重大贡献（1958年逝世）"]},{"year":"1936年","titleList":["葛蘭·穆考特（英语"]},{"year":"1952年","titleList":["艾德瓦爾多·蘇托·德·莫拉，葡萄牙建築師，2011年度普利茲克建築獎得主"]},{"year":"1954年","titleList":["蔡振南，台灣男歌手"]},{"year":"1957年","titleList":["萬梓良，香港演員"]},{"year":"1963年","titleList":["邱瓈寬，台灣女導演"]},{"year":"1966年","titleList":["高木涉，日本配音演员"]},{"year":"1967年","titleList":["麦特·勒布郎，美國演員"]},{"year":"1972年","titleList":["柯藍，中國女演員"]},{"year":"1973年","titleList":["土肥洋一，日本足球運動員"]},{"year":"1978年","titleList":["露薏絲·布朗，第一个试管婴儿"]},{"year":"1980年","titleList":["鄭凱中，台灣演員"]},{"year":"1980年","titleList":["車杜里，韓國足球運動員"]},{"year":"1981年","titleList":["驹野友一，日本足球运动员"]},{"year":"1981年","titleList":["龔詩嘉，台灣歌手"]},{"year":"1981年","titleList":["陈楚生，中国歌手 　　"]},{"year":"1985年","titleList":["尼爾森·小皮奎，巴西F1车手，尼尔森·皮奎特之子。"]},{"year":"1987年","titleList":["阿兰·达瓦卓玛，中国歌手"]},{"year":"1989年","titleList":["陳瑋萱，台灣艺人"]},{"year":"1989年","titleList":["伊一，中国節目主持人"]},{"year":"1991年","titleList":["張筱婕，台灣節目主持人、歌手"]},{"year":"1994年","titleList":["碧安卡·布莎，塞爾維亞女子排球運動員"]}],"deathList":[{"year":"1841年","titleList":["李兆洛，中国地理学家。（1769年出生）"]},{"year":"1946年","titleList":["陶行知，中國教育家。（1891年出生）"]},{"year":"1972年","titleList":["王任叔，笔名巴人，文艺理论家、作家。（1901年出生）"]},{"year":"1983年","titleList":["郑万钧，中国学家。（1904年出生）"]},{"year":"1984年","titleList":["平田昭彥，日本著名演員。（1927年出生）"]},{"year":"1994年","titleList":["林青慧、石济雅，1994年北一女中學生自殺事件兩位女性死者。(均1976年左右出生)"]},{"year":"1995年","titleList":["公文公，日本高級中學的數學教師、數學研究家。（1914年出生）"]},{"year":"2005年","titleList":["陈辛仁，中国外交家。（1915年出生）"]},{"year":"2006年","titleList":["杜照宇，中國人民解放軍的一名中校軍官。（1972年出生）"]},{"year":"2007年","titleList":["裴衡圭，被塔利班殺害的韓國人質。"]},{"year":"2008年","titleList":["蘭迪·波許，卡内基美隆大學教授，曾演說「最後的演講（英语"]},{"year":"2013年","titleList":["聖·卡爾·巴傑瓦（Sant Kaur Bajwa），115歲199天，前任英國在世最長壽的女性。"]},{"year":"2013年","titleList":["穆罕默德·布拉米，突尼西亞政治人物。"]}],"holidayList":["教會：聖雅各日","廣州及港澳地區：粵語日"]}